aws_pcluster_slurm_spawner/__init__.py
aws_pcluster_slurm_spawner/_version.py
aws_pcluster_slurm_spawner/aws_pcluster_slurm_spawner.py
aws_pcluster_slurm_spawner-2023.9.26.dist-info/LICENSE
aws_pcluster_slurm_spawner-2023.9.26.dist-info/METADATA
aws_pcluster_slurm_spawner-2023.9.26.dist-info/WHEEL
aws_pcluster_slurm_spawner-2023.9.26.dist-info/top_level.txt
aws_pcluster_slurm_spawner-2023.9.26.dist-info/RECORD
