Metadata-Version: 2.1
Name: aws-pcluster-slurm-spawner
Version: 2023.9.26
Summary: Extend Jupyterhub's BatchSpawner to deal with AWS ParallelCluster's SLURM environment
Home-page: https://github.com/dabble-of-devops-bioanalyze/aws_pcluster_slurm_spawner
Author: Jillian Rowe
Author-email: jillian@dabbleofdevops.com
License: Apache Software License 2.0
Keywords: aws_pcluster_slurm_spawner
Classifier: Development Status :: 2 - Pre-Alpha
Classifier: Intended Audience :: Developers
Classifier: License :: OSI Approved :: Apache Software License
Classifier: Natural Language :: English
Classifier: Programming Language :: Python :: 3
Classifier: Programming Language :: Python :: 3.6
Classifier: Programming Language :: Python :: 3.7
Classifier: Programming Language :: Python :: 3.8
Requires-Python: >=3.6
License-File: LICENSE
Requires-Dist: batchspawner
Requires-Dist: datasize
Requires-Dist: humanize
Requires-Dist: boto3
Requires-Dist: aws-pcluster-helpers
